jira_worklogger/__init__.py
jira_worklogger/worklogger.py
jira_worklogger-0.1.3.dist-info/METADATA
jira_worklogger-0.1.3.dist-info/WHEEL
jira_worklogger-0.1.3.dist-info/entry_points.txt
jira_worklogger-0.1.3.dist-info/licenses/LICENSE
jira_worklogger-0.1.3.dist-info/RECORD
