Metadata-Version: 2.4
Name: jira-worklogger
Version: 0.1.3
Summary: A CLI utility to track how much time you spent on JIRA tickets
License-Expression: MIT
License-File: LICENSE
Author: Konrad Kleine
Author-email: kkleine@redhat.com
Requires-Python: >=3.10
Classifier: Programming Language :: Python :: 3
Classifier: Programming Language :: Python :: 3.10
Classifier: Programming Language :: Python :: 3.11
Classifier: Programming Language :: Python :: 3.12
Classifier: Programming Language :: Python :: 3.13
Classifier: Programming Language :: Python :: 3.14
Requires-Dist: jira (>=3.8.0,<4.0.0)
Requires-Dist: questionary (>=2.1.0,<3.0.0)
Project-URL: Bug Tracker, https://github.com/kwk/jira-worklogger/issues
Project-URL: Repository, https://github.com/kwk/jira-worklogger
